{
    "/js/realestatelaravel.js": "/js/realestatelaravel.js",
    "/js/manifest.js": "/js/manifest.js",
    "/js/main.12db48dc5d83dbf2675d.js": "/js/main.12db48dc5d83dbf2675d.js",
    "/js/list-properites.ef8abce718d9b7f8cce1.js": "/js/list-properites.ef8abce718d9b7f8cce1.js",
    "/js/create-or-edit-properites.e5883d5c47dd56a251ef.js": "/js/create-or-edit-properites.e5883d5c47dd56a251ef.js",
    "/js/list-banners.89f5d63f0eb96728debf.js": "/js/list-banners.89f5d63f0eb96728debf.js",
    "/js/vendor.404556e98cc8d7e7a966.js": "/js/vendor.404556e98cc8d7e7a966.js",
    "/css/realestatelaravel.css": "/css/realestatelaravel.css",
    "/js/create-or-edit-properites.124c5d01880b397c6542.js": "/js/create-or-edit-properites.124c5d01880b397c6542.js",
    "/js/create-or-edit-properites.23ff34a26599f188baa2.js": "/js/create-or-edit-properites.23ff34a26599f188baa2.js",
    "/js/create-or-edit-properites.000539c137631a7e8e68.js": "/js/create-or-edit-properites.000539c137631a7e8e68.js",
    "/js/create-or-edit-properites.5817f9fbb18b7e0a1c58.js": "/js/create-or-edit-properites.5817f9fbb18b7e0a1c58.js",
    "/js/create-or-edit-properites.6ecad9302f0b6ff18d85.js": "/js/create-or-edit-properites.6ecad9302f0b6ff18d85.js",
    "/js/create-or-edit-properites.23eb128055ef619dc5d6.js": "/js/create-or-edit-properites.23eb128055ef619dc5d6.js",
    "/js/create-or-edit-properites.36a41f77fce22f496203.js": "/js/create-or-edit-properites.36a41f77fce22f496203.js",
    "/js/create-or-edit-properites.b354b79da59637f1d3dd.js": "/js/create-or-edit-properites.b354b79da59637f1d3dd.js",
    "/js/create-or-edit-properites.0bbdba211b15d7ce5aba.js": "/js/create-or-edit-properites.0bbdba211b15d7ce5aba.js",
    "/js/create-or-edit-properites.685e95cd0223352def9c.js": "/js/create-or-edit-properites.685e95cd0223352def9c.js",
    "/js/create-or-edit-properites.48e6f9d0da9da6365e83.js": "/js/create-or-edit-properites.48e6f9d0da9da6365e83.js",
    "/js/create-or-edit-properites.27784042922d2520e7a3.js": "/js/create-or-edit-properites.27784042922d2520e7a3.js",
    "/js/create-or-edit-properites.8bc6eabf0ae346dbf0dc.js": "/js/create-or-edit-properites.8bc6eabf0ae346dbf0dc.js",
    "/js/create-or-edit-properites.38fd8eef506027dfa8b6.js": "/js/create-or-edit-properites.38fd8eef506027dfa8b6.js",
    "/js/create-or-edit-properites.344b627409d9b6e8a006.js": "/js/create-or-edit-properites.344b627409d9b6e8a006.js",
    "/js/create-or-edit-properites.7f72171b34f1540b21c0.js": "/js/create-or-edit-properites.7f72171b34f1540b21c0.js",
    "/js/create-or-edit-properites.51ced21f63701f66b032.js": "/js/create-or-edit-properites.51ced21f63701f66b032.js",
    "/js/create-or-edit-properites.802b1987a0807184ff4d.js": "/js/create-or-edit-properites.802b1987a0807184ff4d.js",
    "/js/create-or-edit-properites.61a63985bc6514775f29.js": "/js/create-or-edit-properites.61a63985bc6514775f29.js",
    "/js/create-or-edit-properites.2cc96516b303754edd73.js": "/js/create-or-edit-properites.2cc96516b303754edd73.js",
    "/js/create-or-edit-properites.824ae77c4f69e417400d.js": "/js/create-or-edit-properites.824ae77c4f69e417400d.js",
    "/js/create-or-edit-properites.ac6610759b6343d11a34.js": "/js/create-or-edit-properites.ac6610759b6343d11a34.js",
    "/js/create-or-edit-properites.318f47bd9cc32d3455d1.js": "/js/create-or-edit-properites.318f47bd9cc32d3455d1.js"
}
